rabbitmq_api_client-0.0.5.dist-info/METADATA
rabbitmq_api_client-0.0.5.dist-info/WHEEL
rabbitmq_api_client-0.0.5.dist-info/licenses/LICENCE
rabbitmq_api_client/__init__.py
rabbitmq_api_client/base.py
rabbitmq_api_client/client.py
rabbitmq_api_client/exceptions.py
rabbitmq_api_client/schemas.py
rabbitmq_api_client-0.0.5.dist-info/RECORD
