Metadata-Version: 2.1
Name: rabbitmq_api_client
Version: 0.0.5
Summary: Http client to manage Rabbitmq admin
Author-Email: Elie Terrien <contact@elie-terrien.fr>
License: MIT
Project-URL: Source, https://github.com/elterrien/rabbitmq_api_client
Requires-Python: >=3.11
Requires-Dist: httpx>=0.25.0
Requires-Dist: pydantic>=2.4.2
